upsidedown.py
ckuehl_upsidedown-0.4.dist-info/DESCRIPTION.rst
ckuehl_upsidedown-0.4.dist-info/METADATA
ckuehl_upsidedown-0.4.dist-info/RECORD
ckuehl_upsidedown-0.4.dist-info/WHEEL
ckuehl_upsidedown-0.4.dist-info/entry_points.txt
ckuehl_upsidedown-0.4.dist-info/metadata.json
ckuehl_upsidedown-0.4.dist-info/top_level.txt
