Metadata-Version: 2.0
Name: ckuehl-upsidedown
Version: 0.4
Summary: Fork that supports Python 3
Home-page: http://github.com/cburgmer/upsidedown
Author: Christoph Burgmer
Author-email: christoph.burgmer@gmail.com
License: MIT
Download-URL: http://github.com/cburgmer/upsidedown/downloads
Platform: UNKNOWN
Classifier: Environment :: Console
Classifier: Intended Audience :: Developers
Classifier: Development Status :: 5 - Production/Stable
Classifier: Operating System :: OS Independent
Classifier: Programming Language :: Python :: 3
Classifier: Programming Language :: Python :: 3.4
Classifier: Programming Language :: Python :: 3.5
Classifier: License :: OSI Approved :: MIT License
Classifier: Topic :: Text Processing
